{"cameraMode":{"drawMode":0,"name":"Shaded","section":"Shading Mode"},"sceneLighting":true,"audioPlay":false,"sceneViewState":{"m_AlwaysRefresh":false,"showFog":true,"showSkybox":true,"showFlares":true,"showImageEffects":true,"showParticleSystems":true,"showVisualEffectGraphs":true,"m_FxEnabled":true},"in2DMode":false,"pivot":{"x":35.789058685302737,"y":7.804043769836426,"z":7.076228141784668},"rotation":{"x":0.028409874066710473,"y":-0.5667786002159119,"z":0.01956162229180336,"w":0.8231478929519653},"size":16.211124420166017,"orthographic":false}